kiwidb/__init__.py
kiwidb/__main__.py
kiwidb/client.py
kiwidb/error.py
kiwidb/protocol.py
kiwidb/server.py
kiwidb-0.0.0a1.dist-info/licenses/LICENSE.md
kiwidb-0.0.0a1.dist-info/METADATA
kiwidb-0.0.0a1.dist-info/WHEEL
kiwidb-0.0.0a1.dist-info/top_level.txt
kiwidb-0.0.0a1.dist-info/RECORD
