Metadata-Version: 2.4
Name: kiwidb
Version: 0.0.0a1
Summary: Small in-memory, key-value database.
Home-page: https://github.com/ernestofgonzalez/kiwidb
Author: Ernesto González
License: Apache License, Version 2.0
Project-URL: Source code, https://github.com/ernestofgonzalez/kiwidb
Project-URL: Issues, https://github.com/ernestofgonzalez/kiwidb/issues
Project-URL: CI, https://github.com/ernestofgonzalez/kiwidb/actions
Classifier: Intended Audience :: Developers
Classifier: Topic :: Software Development :: Libraries
Classifier: Programming Language :: Python :: 3.10
Classifier: Programming Language :: Python :: 3.11
Classifier: Programming Language :: Python :: 3.12
Classifier: Programming Language :: Python :: 3.13
Requires-Python: >=3.10
License-File: LICENSE.md
Requires-Dist: click
Requires-Dist: click-default-group>=1.2.3
Dynamic: author
Dynamic: classifier
Dynamic: description
Dynamic: description-content-type
Dynamic: home-page
Dynamic: license
Dynamic: license-file
Dynamic: project-url
Dynamic: requires-dist
Dynamic: requires-python
Dynamic: summary
